fintag/__init__.py
fintag/client.py
fintag_py-0.1.2.dist-info/licenses/LICENSE
fintag_py-0.1.2.dist-info/METADATA
fintag_py-0.1.2.dist-info/WHEEL
fintag_py-0.1.2.dist-info/top_level.txt
fintag_py-0.1.2.dist-info/RECORD
