Metadata-Version: 2.4
Name: fintag-py
Version: 0.1.2
Summary: The Official Python SDK for FinTag API
Author-email: FinTag <team@fintag.io>
License: Apache-2.0
Project-URL: Homepage, https://github.com/fintag-io/fintag-py
Project-URL: Documentation, https://github.com/fintag-io/fintag-py#readme
Requires-Python: >=3.8
License-File: LICENSE
Requires-Dist: requests>=2.32.3
Dynamic: license-file
